[{"Hour":0,"Count":60},{"Hour":1,"Count":43},{"Hour":2,"Count":28},{"Hour":3,"Count":13},{"Hour":4,"Count":6},{"Hour":5,"Count":5},{"Hour":6,"Count":7},{"Hour":7,"Count":3},{"Hour":8,"Count":16},{"Hour":9,"Count":20},{"Hour":10,"Count":41},{"Hour":11,"Count":96},{"Hour":12,"Count":94},{"Hour":13,"Count":111},{"Hour":14,"Count":87},{"Hour":15,"Count":79},{"Hour":16,"Count":86},{"Hour":17,"Count":68},{"Hour":18,"Count":62},{"Hour":19,"Count":119},{"Hour":20,"Count":155},{"Hour":21,"Count":152},{"Hour":22,"Count":104},{"Hour":23,"Count":77}]