[{"Hour":0,"Count":208},{"Hour":1,"Count":145},{"Hour":2,"Count":84},{"Hour":3,"Count":69},{"Hour":4,"Count":64},{"Hour":5,"Count":28},{"Hour":6,"Count":32},{"Hour":7,"Count":18},{"Hour":8,"Count":67},{"Hour":9,"Count":150},{"Hour":10,"Count":256},{"Hour":11,"Count":394},{"Hour":12,"Count":427},{"Hour":13,"Count":526},{"Hour":14,"Count":528},{"Hour":15,"Count":402},{"Hour":16,"Count":399},{"Hour":17,"Count":302},{"Hour":18,"Count":277},{"Hour":19,"Count":406},{"Hour":20,"Count":453},{"Hour":21,"Count":408},{"Hour":22,"Count":380},{"Hour":23,"Count":247}]